rob_norm/__init__.py
rob_norm/rob_norm.py
rob_norm/sim_data.py
rob_norm-1.0.1.dist-info/WHEEL
rob_norm-1.0.1.dist-info/METADATA
rob_norm-1.0.1.dist-info/RECORD
