Metadata-Version: 2.3
Name: rob-norm
Version: 1.0.1
Summary: Python implementation of RobNorm, a robust normalization method for labeled quantitative proteomics data.
Author: Tom-Julux
Author-email: Tom-Julux <hello@tomjulux.me>
Requires-Dist: numpy>=2.3.5
Requires-Dist: pandas>=2.3.3
Requires-Dist: scipy>=1.16.3
Requires-Python: >=3.11
